{
    "pres_name": "Herbert Hoover",
    "byline": "31st\u00a0President of the United States:\u00a01929 \u2010 1933",
    "title": "Message to a Testimony Dinner Honoring Louis Lipsky.",
    "date": "1930-12-07",
    "text": "My dear Mr. Deutsch:\n\nI am glad to learn of the honor to be paid to Mr. Louis Lipsky at a testimonal dinner on November 16th, and I will be obliged if you will express my cordial congratulations to him and my deep appreciation of his long and valuable service to the development of the Jewish cultural life of America. Yours faithfully,\n\nHERBERT HOOVER",
    "garbage_collected": [
        "[Released December 7, 1930. Dated October 23, 1930]",
        "[Bernard S. Deutsch, chairman, Executive Committee, Louis Lipsky Testimonial Committee, 122 West 42nd St., New York City]"
    ]
}