{
    "pres_name": "Lyndon B. Johnson",
    "byline": "36th\u00a0President of the United States:\u00a01963 \u2010 1969",
    "title": "Message to Senora Schick on the Death of President Rene Schick of Nicaragua.",
    "date": "1966-08-03",
    "text": "I WAS SADDENED to learn of the death of President Rene Schick. Please accept Mrs. Johnson's and my deepest personal sympathy in this sorrowful moment.\n\nWe recall the happy time we had when he visited us two months ago. The Hemisphere will miss him.\n\nLYNDON B. JOHNSON",
    "garbage_collected": [
        "[Mrs. Carmen Renasco de Schick, Casa Presidential, Managua, Nicaragua]"
    ]
}