{
    "pres_name": "Lyndon B. Johnson",
    "byline": "36th\u00a0President of the United States:\u00a01963 \u2010 1969",
    "title": "Message to President Trejos Following the Eruption of a Volcano in Costa Rica.",
    "date": "1968-07-31",
    "text": "Dear Mr. President:\n\nI was distressed to learn that a long dormant volcano has erupted in Costa Rica resulting in considerable loss of life, personal injury and material damage. I am asking our Embassy to work with you on emergency relief measures. Please let us know how we can be of help. Sincerely,\n\nLYNDON B. JOHNSON",
    "garbage_collected": [
        "[The Honorable Jose Joaquin Trejos Fernandez, President of Costa Rica]"
    ]
}