{
    "pres_name": "Jimmy Carter",
    "byline": "39th\u00a0President of the United States:\u00a01977 \u2010 1981",
    "title": "Budget Rescission and Deferrals Message to the Congress.",
    "date": "1980-02-20",
    "text": "To the Congress of the United States:\n\nIn accordance with the Impoundment Control Act of 1974, I herewith report one revision to a previously transmitted rescission proposal decreasing the amount proposed by $6.4 million. In addition, I am reporting two new deferrals of budget authority totalling $20.0 million and two revisions to previously transmitted deferrals increasing the amount deferred by $13.9 million.\n\nThe revision to the rescission proposal affects the Health Resources Administration of the Department of Health, Education, and Welfare.\n\nThe new deferrals and revisions to existing deferrals involve programs in the Departments of Agriculture, Health, Education, and Welfare, and the Treasury.\n\nThe details of the revised rescission proposal and the deferrals are contained in the attached reports.\n\nJIMMY CARTER The White House, February 20, 1980.",
    "garbage_collected": []
}