{
    "pres_name": "Dwight D. Eisenhower",
    "byline": "34th\u00a0President of the United States:\u00a01953 \u2010 1961",
    "title": "Message to President Po Sun Yun of Korea.",
    "date": "1960-08-29",
    "text": "Dear Mr. President:\n\nIt is with great pleasure that I extend my congratulations and best wishes to you upon your assumption of the office of President of the Republic of Korea.\n\nI wish you all success in discharging the responsibilities of this high office, your accession to which bears eloquent testimony to the trust and confidence reposed in you as a distinguished leader of a great people. Sincerely,\n\nDWIGHT D. EISENHOWER",
    "garbage_collected": []
}